{"prerequisites": {"ACCT*2220": [], "ACCT*1220": [], "ACCT*2230": [{"type": "OR", "groups": ["ACCT*1220", "ACCT*2220"]}], "ACCT*3330": [{"type": "OR", "groups": ["ACCT*1220", "ACCT*2220"]}], "ACCT*3280": [{"type": "AND", "groups": ["ACCT*3330"]}], "ACCT*3340": [{"type": "AND", "groups": ["ACCT*3330"]}], "ACCT*3350": [{"type": "AND", "groups": ["ACCT*3330"]}], "BUS*3330": [], "BUS*3340": [], "ACCT*4220": [{"type": "AND", "groups": [{"type": "OR", "groups": ["ACCT*3330", "BUS*3330"]}, {"type": "OR", "groups": ["ACCT*3340", "BUS*3340"]}]}], "ACCT*3230": [], "BUS*3230": [], "ACCT*4230": [{"type": "OR", "groups": ["ACCT*3230", "BUS*3230"]}], "BUS*3280": [], "ACCT*4270": [{"type": "OR", "groups": ["ACCT*3280", "BUS*3280"]}], "BUS*3350": [], "ACCT*4350": [{"type": "OR", "groups": ["ACCT*3350", "BUS*3350"]}]}, "restrictions": {"ACCT*2220": [], "ACCT*1220": [{"type": "AND", "groups": ["ACCT*2220"]}], "ACCT*2230": [], "ACCT*3330": [], "ACCT*3280": [], "ACCT*3340": [], "ACCT*3350": [], "BUS*3330": [], "BUS*3340": [], "ACCT*4220": [], "ACCT*3230": [], "BUS*3230": [], "ACCT*4230": [], "BUS*3280": [], "ACCT*4270": [], "BUS*3350": [], "ACCT*4350": []}}
