{"prerequisites": {"CIS*1200": [], "CIS*1000": [], "CIS*1250": [], "CIS*1500": [], "CIS*1300": [], "CIS*1910": [], "CIS*2500": [], "CIS*2030": [{"type": "AND", "groups": ["CIS*1910", "CIS*2500"]}], "CIS*2430": [{"type": "AND", "groups": ["CIS*2500"]}], "ENGG*1500": [], "MATH*1160": [{"type": "OR", "groups": ["4U Calculus and Vectors", "4U Advanced Functions"]}], "MATH*2150": [], "MATH*2160": [], "MATH*2000": [{"type": "OR", "groups": ["IPS*1500", "MATH*1080", "MATH*1160", "MATH*1200"]}], "IPS*1500": [{"type": "OR", "groups": ["4U Physics", "PHYS*1020", "PHYS*1300"]}], "PHYS*1020": [], "PHYS*1300": [], "PHYS*1070": [], "MATH*1080": [{"type": "OR", "groups": ["4U Advanced Functions", "4U Advanced Functions and Calculus", "equivalent"]}], "MATH*1200": [{"type": "OR", "groups": ["4U Calculus and Vectors", "4U Advanced Functions and Calculus", "Grade 12 Calculus"]}], "PHYS*1000": [], "PHYS*1080": [{"type": "AND", "groups": [{"type": "OR", "groups": ["4U Physics", "PHYS*1020", "PHYS*1300"]}, "4U Mathematics"]}], "CIS*2520": [{"type": "AND", "groups": ["CIS*2500", {"type": "OR", "groups": ["CIS*1910", "ENGG*1500", "MATH*2000"]}]}], "CIS*2750": [{"type": "AND", "groups": ["CIS*2430", "CIS*2520"]}], "CIS*3110": [], "CIS*3050": [{"type": "AND", "groups": ["CIS*3110"]}], "ENGG*3640": [{"type": "AND", "groups": ["ENGG*2410", "ENGG*2450"]}], "ENGG*2410": [{"type": "AND", "groups": ["PHYS*1130", {"type": "OR", "groups": ["CIS*1300", "CIS*1500"]}]}], "PHYS*1130": [{"type": "AND", "groups": [{"type": "OR", "groups": ["4U Calculus and Vectors", "equivalent"]}, {"type": "OR", "groups": ["4U Physics", "equivalent"]}]}], "ENGG*2450": [], "CIS*3090": [{"type": "AND", "groups": [{"type": "OR", "groups": ["CIS*2030", "ENGG*3640"]}, "CIS*3110"]}], "STAT*2040": [{"type": "OR", "groups": ["4U Calculus and Vectors", "Advanced Functions and Calculus", "OAC Calculus", "MATH*1080"]}], "STAT*2060": [{"type": "OR", "groups": [{"type": "OR", "groups": ["4U mathematics", "equivalent"]}, {"type": "CREDITS", "code": "mathematics", "credits": 0.5}]}], "STAT*2080": [{"type": "OR", "groups": [{"type": "OR", "groups": ["4U mathematics", "equivalent"]}, {"type": "CREDITS", "code": "mathematics.", "credits": 0.5}]}], "STAT*2100": [], "STAT*2120": [{"type": "OR", "groups": ["IPS*1510", "MATH*1210", "MATH*2080"]}], "IPS*1510": [], "MATH*1210": [], "MATH*2080": [], "STAT*2230": [], "CIS*2460": [], "CIS*3130": [{"type": "AND", "groups": ["CIS*2500", "STAT*2040"]}], "CIS*3490": [], "CIS*3150": [{"type": "AND", "groups": ["CIS*2750", "CIS*3490"]}], "CIS*3210": [{"type": "AND", "groups": ["CIS*3110"]}], "CIS*2250": [], "CIS*3250": [{"type": "AND", "groups": ["CIS*2250", "CIS*2500"]}], "CIS*3760": [{"type": "AND", "groups": ["CIS*3750"]}], "CIS*3750": [{"type": "AND", "groups": ["CIS*2750"]}], "CIS*3260": [{"type": "AND", "groups": ["CIS*2750", "CIS*3250", "CIS*3760"]}], "CIS*3530": [{"type": "AND", "groups": ["CIS*2520"]}], "CIS*4010": [{"type": "AND", "groups": ["CIS*3110"]}], "CIS*4020": [{"type": "AND", "groups": ["CIS*2750", "MATH*1160", "STAT*2040"]}], "CIS*4150": [{"type": "OR", "groups": ["CIS*3750", "CIS*3760"]}], "CIS*4300": [{"type": "AND", "groups": ["CIS*3110", {"type": "OR", "groups": ["CIS*3750", "CIS*3760"]}]}], "CIS*4110": [], "CIS*4510": [{"type": "AND", "groups": ["CIS*3210"]}], "CIS*4780": [{"type": "AND", "groups": ["CIS*3490", {"type": "OR", "groups": ["CIS*3750", "CIS*3760"]}, {"type": "OR", "groups": ["CIS*2460", "STAT*2040"]}]}], "CIS*4900": [{"type": "CREDITS", "code": "CIS", "credits": 7.0}], "CIS*4910": [{"type": "AND", "groups": ["CIS*4900"]}], "CIS*6320": [], "CIS*6510": [], "CIS*6540": [], "CIS*6550": [], "CIS*6650": [], "CIS*2420": []}, "restrictions": {"CIS*1200": [], "CIS*1000": [{"type": "AND", "groups": ["CIS*1200"]}], "CIS*1250": [], "CIS*1500": [{"type": "AND", "groups": ["CIS*1300"]}], "CIS*1300": [{"type": "AND", "groups": ["CIS*1500"]}], "CIS*1910": [], "CIS*2500": [], "CIS*2030": [], "CIS*2430": [], "ENGG*1500": [{"type": "AND", "groups": ["MATH*1160", "MATH*2150", "MATH*2160"]}], "MATH*1160": [{"type": "AND", "groups": ["ENGG*1500", "MATH*2150", "MATH*2160"]}], "MATH*2150": [], "MATH*2160": [], "MATH*2000": [], "IPS*1500": [{"type": "AND", "groups": ["MATH*1080", "MATH*1200", "PHYS*1000", "PHYS*1080"]}], "PHYS*1020": [], "PHYS*1300": [{"type": "AND", "groups": ["SPH 4U", "PHYS*1020", "PHYS*1070"]}], "PHYS*1070": [], "MATH*1080": [{"type": "AND", "groups": ["IPS*1500", "MATH*1200"]}], "MATH*1200": [{"type": "AND", "groups": ["IPS*1500", "MATH*1080"]}], "PHYS*1000": [], "PHYS*1080": [{"type": "AND", "groups": ["IPS*1500", "PHYS*1000"]}], "CIS*2520": [], "CIS*2750": [], "CIS*3110": [], "CIS*3050": [], "ENGG*3640": [], "ENGG*2410": [], "PHYS*1130": [{"type": "AND", "groups": ["IPS*1500", "PHYS*1080"]}], "ENGG*2450": [], "CIS*3090": [], "STAT*2040": [{"type": "AND", "groups": ["STAT*2060", "STAT*2080", "STAT*2120", "STAT*2230"]}], "STAT*2060": [{"type": "AND", "groups": ["STAT*2040", "STAT*2080", "STAT*2120"]}], "STAT*2080": [], "STAT*2100": [], "STAT*2120": [{"type": "AND", "groups": ["STAT*2040", "STAT*2060", "STAT*2080", "STAT*2100"]}], "IPS*1510": [], "MATH*1210": [], "MATH*2080": [], "STAT*2230": [], "CIS*2460": [], "CIS*3130": [{"type": "AND", "groups": ["CIS*2460"]}], "CIS*3490": [], "CIS*3150": [], "CIS*3210": [], "CIS*2250": [], "CIS*3250": [], "CIS*3760": [], "CIS*3750": [], "CIS*3260": [], "CIS*3530": [], "CIS*4010": [], "CIS*4020": [], "CIS*4150": [], "CIS*4300": [], "CIS*4110": [], "CIS*4510": [{"type": "AND", "groups": ["CIS*4110"]}], "CIS*4780": [], "CIS*4900": [{"type": "AND", "groups": ["Instructor consent required."]}], "CIS*4910": [{"type": "AND", "groups": ["Instructor consent required."]}], "CIS*6320": [], "CIS*6510": [{"type": "AND", "groups": ["Student registered in the MCTI program."]}], "CIS*6540": [{"type": "AND", "groups": ["Student registered in the MCTI program."]}], "CIS*6550": [], "CIS*6650": [], "CIS*2420": []}}
